README.rst
setup.cfg
setup.py
src/config_loader/__init__.py
src/config_loader/_config_loader.py
src/config_loader/_freeze.py
src/config_loader/config_example.yaml
src/config_loader/schema_example.yaml
src/datapunt_config_loader.egg-info/PKG-INFO
src/datapunt_config_loader.egg-info/SOURCES.txt
src/datapunt_config_loader.egg-info/dependency_links.txt
src/datapunt_config_loader.egg-info/requires.txt
src/datapunt_config_loader.egg-info/top_level.txt