Metadata-Version: 1.2
Name: datapunt-config-loader
Version: 1.0.1
Summary: Loads Yaml configuration files
Home-page: https://github.com/Amsterdam/config_loader
Author: Amsterdam City Data
Author-email: datapunt@amsterdam.nl
License: Mozilla Public License Version 2.0
Platform: UNKNOWN
Classifier: License :: OSI Approved :: Mozilla Public License 2.0 (MPL 2.0)
Classifier: Programming Language :: Python
Classifier: Programming Language :: Python :: 3.6
Requires-Python: ~=3.6
